fastml_engine/__init__.py
fastml_engine/cli.py
fastml_engine/core.py
fastml_engine/log.py
fastml_engine/modelservice.py
fastml_engine/server.py
fastml_engine/docs/health.yaml
fastml_engine/docs/predict.yaml
fastml_engine/exception/__init__.py
fastml_engine/exception/infer_exception.py
fastml_engine/exception/load_exception.py
fastml_engine/utils/__init__.py
fastml_engine/utils/process.py
fastml_engine-1.0.7.dist-info/LICENSE
fastml_engine-1.0.7.dist-info/METADATA
fastml_engine-1.0.7.dist-info/WHEEL
fastml_engine-1.0.7.dist-info/entry_points.txt
fastml_engine-1.0.7.dist-info/top_level.txt
fastml_engine-1.0.7.dist-info/RECORD
