Metadata-Version: 2.1
Name: fastml-engine
Version: 1.0.7
Summary: A web server for deploy ml/dl model
Home-page: UNKNOWN
Author: HaiTao Hou
Author-email: hou610433155@163.com
License: MIT
Project-URL: Source Code, https://github.com/fast-mlops/fastml-engine
Platform: UNKNOWN
Classifier: Programming Language :: Python :: 3
Classifier: License :: OSI Approved :: MIT License
Classifier: Operating System :: OS Independent
Requires-Python: >=3.6
License-File: LICENSE
Requires-Dist: Flask
Requires-Dist: flasgger
Requires-Dist: numpy
Requires-Dist: six
Requires-Dist: gevent
Requires-Dist: Werkzeug
Requires-Dist: concurrent-log-handler (==0.9.16)
Requires-Dist: portalocker (==1.7.0)
Requires-Dist: click (>=7.0gunicorn) ; platform_system != "Windows"
Requires-Dist: waitress ; platform_system == "Windows"
